libsv/__init__.py
libsv/arbiters/ring_arbiter.sv
libsv/bit_ops/rotate.sv
libsv/coders/bcd_decoder.sv
libsv/coders/bcd_encoder.sv
libsv/coders/decoder_8b10b.sv
libsv/coders/encoder_8b10b.sv
libsv/coders/onehot_priority_encoder.sv
libsv/coders/priority_encoder.sv
libsv/counters/binary_counter.sv
libsv/fifos/skid_buffer.sv
libsv/latches/sr_latch.sv
libsv/math/full_adder.sv
libsv/math/half_adder.sv
libsv/muxes/onehot_mux.sv
libsv-0.2.1.dist-info/LICENSE
libsv-0.2.1.dist-info/WHEEL
libsv-0.2.1.dist-info/METADATA
libsv-0.2.1.dist-info/RECORD
