Metadata-Version: 2.1
Name: libsv
Version: 0.2.1
Summary: An open source, parameterized SystemVerilog hardware IP library
Home-page: https://libsv.readthedocs.io/en/latest/
License: MIT
Keywords: SystemVerilog,Verilog,Hardware,IP,Cocotb
Author: Ben Sampson
Author-email: bensampson5@gmail.com
Maintainer: Ben Sampson
Maintainer-email: bensampson5@gmail.com
Requires-Python: >=3.6.2,<4.0.0
Classifier: License :: OSI Approved :: MIT License
Classifier: Programming Language :: Python :: 3
Classifier: Programming Language :: Python :: 3.10
Classifier: Programming Language :: Python :: 3.7
Classifier: Programming Language :: Python :: 3.8
Classifier: Programming Language :: Python :: 3.9
Classifier: Topic :: Scientific/Engineering
Classifier: Topic :: Scientific/Engineering :: Electronic Design Automation (EDA)
Classifier: Topic :: System :: Hardware
Project-URL: Bug Tracker, https://github.com/bensampson5/libsv/issues
Project-URL: Documentation, https://libsv.readthedocs.io/en/latest/
Project-URL: Repository, https://github.com/bensampson5/libsv
